kc3zvd/iot_state/__about__.py
kc3zvd/iot_state/__init__.py
kc3zvd/iot_state/__main__.py
kc3zvd/iot_state/devices.py
kc3zvd/iot_state/utility.py
kc3zvd/iot_state/cli/__init__.py
kc3zvd/iot_state/cli/core/mqtt.py
kc3zvd/iot_state/publishers/__init__.py
kc3zvd/iot_state/publishers/mqtt.py
kc3zvd/iot_state/subscribers/__init__.py
kc3zvd/iot_state/subscribers/redis.py
kc3zvd/iot_state/subscribers/wled.py
kc3zvd/iot_state/workers/__init__.py
kc3zvd/iot_state/workers/wled.py
kc3zvd_iot_state-0.3.0.dist-info/METADATA
kc3zvd_iot_state-0.3.0.dist-info/WHEEL
kc3zvd_iot_state-0.3.0.dist-info/entry_points.txt
kc3zvd_iot_state-0.3.0.dist-info/licenses/LICENSE.txt
kc3zvd_iot_state-0.3.0.dist-info/RECORD
